libarbitrage/__init__.py
libarbitrage/lib.py
libarbitrage-0.0.21.dist-info/LICENSE
libarbitrage-0.0.21.dist-info/METADATA
libarbitrage-0.0.21.dist-info/WHEEL
libarbitrage-0.0.21.dist-info/top_level.txt
libarbitrage-0.0.21.dist-info/RECORD
